METI/METI.py
METI/__init__.py
metiforst-0.5.dist-info/METADATA
metiforst-0.5.dist-info/WHEEL
metiforst-0.5.dist-info/top_level.txt
metiforst-0.5.dist-info/RECORD
