Metadata-Version: 2.2
Name: METIforST
Version: 0.5
Summary: METI: Deep profiling of tumor ecosystems by integrating cell morphology and spatial transcriptomics
Home-page: https://github.com/Flashiness/METI
Author: Jiahui Jiang
Author-email: jjiang6@mdanderson.org
Requires-Dist: python-igraph
Requires-Dist: torch
Requires-Dist: pandas
Requires-Dist: numpy
Requires-Dist: scipy
Requires-Dist: scanpy
Requires-Dist: anndata
Requires-Dist: louvain
Requires-Dist: scikit-learn
Requires-Dist: numba
Requires-Dist: TESLAforST
Dynamic: author
Dynamic: author-email
Dynamic: description
Dynamic: description-content-type
Dynamic: home-page
Dynamic: requires-dist
Dynamic: summary
